LICENSE
MANIFEST.in
README.rst
setup.py
setupegg.py
docs/index.rst
docs/manual.rst
kabuki/__init__.py
kabuki/analyze.py
kabuki/distributions.py
kabuki/experiments.py
kabuki/generate.py
kabuki/hierarchical.py
kabuki/step_methods.py
kabuki/utils.py
kabuki.egg-info/PKG-INFO
kabuki.egg-info/SOURCES.txt
kabuki.egg-info/dependency_links.txt
kabuki.egg-info/requires.txt
kabuki.egg-info/top_level.txt
kabuki/tests/__init__.py
kabuki/tests/test_analyze.py
kabuki/tests/test_generate.py
kabuki/tests/test_hierarchical.py
kabuki/tests/test_step_methods.py
kabuki/tests/utils.py